oncoplot_extractor/__init__.py
oncoplot_extractor/errors.py
oncoplot_extractor/main.py
oncoplot_extractor/plotter.py
oncoplot_extractor-1.0.5.dist-info/METADATA
oncoplot_extractor-1.0.5.dist-info/WHEEL
oncoplot_extractor-1.0.5.dist-info/top_level.txt
oncoplot_extractor-1.0.5.dist-info/RECORD
