Metadata-Version: 2.1
Name: oncoplot-extractor
Version: 1.0.5
Summary: General Toolkit for OncoPlot written in Python
Home-page: https://github.com/regmibijay/oncoplot-extractor
Author: Bijay Regmi
Author-email: oncoplot-extractor@regdelivery.de
License: GNU (GPLv3)
Platform: UNKNOWN
Classifier: Programming Language :: Python :: 3
Classifier: License :: OSI Approved :: GNU General Public License v3 (GPLv3)
Classifier: Operating System :: OS Independent
Requires-Python: >=3.6
Requires-Dist: pandas
Requires-Dist: pillow
Requires-Dist: openpyxl
Requires-Dist: httpx
